microse/__init__.py
microse/app.py
microse/proxy.py
microse/utils.py
microse/rpc/__init.__.py
microse/rpc/channel.py
microse/rpc/client.py
microse/rpc/server.py
microse-1.1.2.dist-info/LICENSE
microse-1.1.2.dist-info/METADATA
microse-1.1.2.dist-info/WHEEL
microse-1.1.2.dist-info/top_level.txt
microse-1.1.2.dist-info/RECORD
