Metadata-Version: 2.1
Name: microse
Version: 1.1.2
Summary: Micro Remote Object Serving Engine
Home-page: https://github.com/microse-rpc/microse-py
Author: A-yon Lee
Author-email: i@hyurl.com
License: UNKNOWN
Keywords: rpc,micro-service,module-proxy
Platform: UNKNOWN
Classifier: Programming Language :: Python :: 3
Classifier: License :: OSI Approved :: MIT License
Classifier: Operating System :: OS Independent
Requires-Python: >=3.6
License-File: LICENSE
Requires-Dist: websockets (>=8.0)
